{
  "main": {
    "id": "228e5bf71289da52",
    "type": "split",
    "children": [
      {
        "id": "6b9bde43cdb1f90c",
        "type": "tabs",
        "children": [
          {
            "id": "a44c25c53c8c5007",
            "type": "leaf",
            "state": {
              "type": "markdown",
              "state": {
                "file": "Ideas For Given Items.md",
                "mode": "source",
                "source": false
              },
              "icon": "lucide-file",
              "title": "Ideas For Given Items"
            }
          },
          {
            "id": "bb2cdff21c1f0e57",
            "type": "leaf",
            "state": {
              "type": "markdown",
              "state": {
                "file": "Randomization Ideas.md",
                "mode": "source",
                "source": false
              },
              "icon": "lucide-file",
              "title": "Randomization Ideas"
            }
          },
          {
            "id": "5c1f5764538287bb",
            "type": "leaf",
            "state": {
              "type": "markdown",
              "state": {
                "file": "Item Packages.md",
                "mode": "source",
                "source": false
              },
              "icon": "lucide-file",
              "title": "Item Packages"
            }
          },
          {
            "id": "079b265db7852a17",
            "type": "leaf",
            "state": {
              "type": "markdown",
              "state": {
                "file": "Ideas For Victory Conditions.md",
                "mode": "source",
                "source": false
              },
              "icon": "lucide-file",
              "title": "Ideas For Victory Conditions"
            }
          }
        ],
        "currentTab": 1
      }
    ],
    "direction": "vertical"
  },
  "left": {
    "id": "c592cafe781c6415",
    "type": "split",
    "children": [
      {
        "id": "9b55c28f7ab04091",
        "type": "tabs",
        "children": [
          {
            "id": "e34691277d3ded42",
            "type": "leaf",
            "state": {
              "type": "file-explorer",
              "state": {
                "sortOrder": "alphabetical",
                "autoReveal": false
              },
              "icon": "lucide-folder-closed",
              "title": "Files"
            }
          },
          {
            "id": "605dd6810f0a055e",
            "type": "leaf",
            "state": {
              "type": "search",
              "state": {
                "query": "",
                "matchingCase": false,
                "explainSearch": false,
                "collapseAll": false,
                "extraContext": false,
                "sortOrder": "alphabetical"
              },
              "icon": "lucide-search",
              "title": "Search"
            }
          },
          {
            "id": "de7a38e5745bf0e1",
            "type": "leaf",
            "state": {
              "type": "bookmarks",
              "state": {},
              "icon": "lucide-bookmark",
              "title": "Bookmarks"
            }
          }
        ]
      }
    ],
    "direction": "horizontal",
    "width": 300
  },
  "right": {
    "id": "69bbc3ccff86818c",
    "type": "split",
    "children": [
      {
        "id": "d22df419d168feb9",
        "type": "tabs",
        "children": [
          {
            "id": "5e33efc567ab5b0b",
            "type": "leaf",
            "state": {
              "type": "backlink",
              "state": {
                "file": "Randomization Ideas.md",
                "collapseAll": false,
                "extraContext": false,
                "sortOrder": "alphabetical",
                "showSearch": false,
                "searchQuery": "",
                "backlinkCollapsed": false,
                "unlinkedCollapsed": true
              },
              "icon": "links-coming-in",
              "title": "Backlinks for Randomization Ideas"
            }
          },
          {
            "id": "e62c9db4ee3b0a9b",
            "type": "leaf",
            "state": {
              "type": "outgoing-link",
              "state": {
                "file": "Ideas For Given Items.md",
                "linksCollapsed": false,
                "unlinkedCollapsed": true
              },
              "icon": "links-going-out",
              "title": "Outgoing links from Ideas For Given Items"
            }
          },
          {
            "id": "5d603e146963fb60",
            "type": "leaf",
            "state": {
              "type": "tag",
              "state": {
                "sortOrder": "frequency",
                "useHierarchy": true,
                "showSearch": false,
                "searchQuery": ""
              },
              "icon": "lucide-tags",
              "title": "Tags"
            }
          },
          {
            "id": "81eb1f3fa5b3d00b",
            "type": "leaf",
            "state": {
              "type": "all-properties",
              "state": {
                "sortOrder": "frequency",
                "showSearch": false,
                "searchQuery": ""
              },
              "icon": "lucide-archive",
              "title": "All properties"
            }
          },
          {
            "id": "b2e3c6899aa75246",
            "type": "leaf",
            "state": {
              "type": "outline",
              "state": {
                "file": "Ideas For Given Items.md",
                "followCursor": false,
                "showSearch": false,
                "searchQuery": ""
              },
              "icon": "lucide-list",
              "title": "Outline of Ideas For Given Items"
            }
          }
        ]
      }
    ],
    "direction": "horizontal",
    "width": 300,
    "collapsed": true
  },
  "left-ribbon": {
    "hiddenItems": {
      "switcher:Open quick switcher": false,
      "graph:Open graph view": false,
      "canvas:Create new canvas": false,
      "daily-notes:Open today's daily note": false,
      "templates:Insert template": false,
      "command-palette:Open command palette": false,
      "bases:Create new base": false,
      "templater-obsidian:Templater": false
    }
  },
  "active": "bb2cdff21c1f0e57",
  "lastOpenFiles": [
    "Ideas For Victory Conditions.md",
    "Ideas For Location Checks.md",
    "Item Packages.md",
    "Randomization Ideas.md",
    "Ideas For Given Items.md",
    "Welcome.md",
    "run/saves/New World/playerdata/5031b283-213a-3769-9d06-07f0ca40feb8.dat_old",
    "run/saves/New World/advancements/5031b283-213a-3769-9d06-07f0ca40feb8.json",
    "run/saves/New World/stats/5031b283-213a-3769-9d06-07f0ca40feb8.json",
    "run/saves/New World/playerdata/5031b283-213a-3769-9d06-07f0ca40feb8.dat",
    "run/saves/New World/level13413995635377533075.dat",
    "build/resources/main/data/minecraftarchipelago/apstages/stages/early_game.json",
    "build/resources/main/data/minecraftarchipelago/apstages/packages/starter_tools.json",
    "build/resources/main/data/minecraftarchipelago/apstages/stages",
    "build/resources/main/data/minecraftarchipelago/apstages/packages",
    "build/resources/main/data/minecraftarchipelago/apstages",
    "create a link.md",
    "run/saves/New World/icon.png",
    "build/resources/main/assets/minecraftarchipelago/icon.png",
    "src/main/resources/assets/minecraftarchipelago/icon.png",
    "run/saves/New World (1)/icon.png",
    "build/resources/main/assets/minecraft-archipelago/icon.png",
    "src/main/resources/assets/minecraft-archipelago/icon.png",
    "README.md"
  ]
}